nanoidp/__init__.py
nanoidp/__main__.py
nanoidp/app.py
nanoidp/config.py
nanoidp/exceptions.py
nanoidp/mcp_server.py
nanoidp/wizard.py
nanoidp/routes/__init__.py
nanoidp/routes/api.py
nanoidp/routes/oauth.py
nanoidp/routes/saml.py
nanoidp/routes/ui.py
nanoidp/services/__init__.py
nanoidp/services/audit.py
nanoidp/services/auth_code.py
nanoidp/services/crypto.py
nanoidp/services/token.py
nanoidp/services/yaml_writer.py
nanoidp/templates/audit.html
nanoidp/templates/authorize.html
nanoidp/templates/base.html
nanoidp/templates/claims.html
nanoidp/templates/clients.html
nanoidp/templates/clients_form.html
nanoidp/templates/device.html
nanoidp/templates/index.html
nanoidp/templates/keys.html
nanoidp/templates/login.html
nanoidp/templates/logout.html
nanoidp/templates/settings.html
nanoidp/templates/test.html
nanoidp/templates/user_detail.html
nanoidp/templates/users.html
nanoidp/templates/users_form.html
nanoidp-1.2.2.dist-info/METADATA
nanoidp-1.2.2.dist-info/WHEEL
nanoidp-1.2.2.dist-info/entry_points.txt
nanoidp-1.2.2.dist-info/licenses/LICENSE
nanoidp-1.2.2.dist-info/RECORD
