Metadata-Version: 2.4
Name: nanoidp
Version: 1.2.2
Summary: A lightweight, configurable Identity Provider for development and testing
Project-URL: Homepage, https://github.com/cdelmonte-zg/nanoidp
Project-URL: Documentation, https://github.com/cdelmonte-zg/nanoidp#readme
Project-URL: Repository, https://github.com/cdelmonte-zg/nanoidp.git
Project-URL: Issues, https://github.com/cdelmonte-zg/nanoidp/issues
Author: Christian Del Monte
License-Expression: MIT
License-File: LICENSE
Keywords: authentication,development,identity-provider,idp,mock,oauth2,oidc,saml,testing
Classifier: Development Status :: 4 - Beta
Classifier: Environment :: Web Environment
Classifier: Framework :: Flask
Classifier: Intended Audience :: Developers
Classifier: License :: OSI Approved :: MIT License
Classifier: Operating System :: OS Independent
Classifier: Programming Language :: Python :: 3
Classifier: Programming Language :: Python :: 3.10
Classifier: Programming Language :: Python :: 3.11
Classifier: Programming Language :: Python :: 3.12
Classifier: Topic :: Internet :: WWW/HTTP :: WSGI :: Application
Classifier: Topic :: Security
Classifier: Topic :: Software Development :: Testing
Requires-Python: >=3.10
Requires-Dist: bcrypt>=5.0.0
Requires-Dist: cryptography>=46.0.3
Requires-Dist: flask-cors>=6.0.2
Requires-Dist: flask-limiter>=4.1.1
Requires-Dist: flask>=3.0.0
Requires-Dist: lxml>=6.0.2
Requires-Dist: mcp>=1.0.0
Requires-Dist: pydantic>=2.0.0
Requires-Dist: pyjwt>=2.8.0
Requires-Dist: pyyaml>=6.0
Requires-Dist: signxml>=4.2.0
Provides-Extra: dev
Requires-Dist: black>=25.12.0; extra == 'dev'
Requires-Dist: pytest-asyncio>=1.3.0; extra == 'dev'
Requires-Dist: pytest-cov>=7.0.0; extra == 'dev'
Requires-Dist: pytest>=9.0.2; extra == 'dev'
Requires-Dist: ruff>=0.1.0; extra == 'dev'
